nettime_py/VERSION
nettime_py/__init__.py
nettime_py/api.py
nettime_py/config.py
nettime_py/const.py
nettime_py/exceptions.py
nettime_py/version.py
nettime_py/handlers/__init__.py
nettime_py/handlers/clockings.py
nettime_py/handlers/containers/__init__.py
nettime_py/handlers/containers/base.py
nettime_py/handlers/containers/employee.py
nettime_py/handlers/containers/paginator.py
nettime_py/handlers/containers/planning.py
nettime_py/handlers/containers/query.py
nettime_py/handlers/containers/reader.py
nettime_py/schemas/__init__.py
nettime_py/schemas/app_index.py
nettime_py/schemas/app_settings.py
nettime_py/schemas/base.py
nettime_py/schemas/clockings.py
nettime_py/schemas/containers/__init__.py
nettime_py/schemas/containers/base.py
nettime_py/schemas/containers/detail/__init__.py
nettime_py/schemas/containers/detail/base.py
nettime_py/schemas/containers/detail/employees.py
nettime_py/schemas/containers/detail/planning.py
nettime_py/schemas/containers/detail/readers.py
nettime_py/schemas/containers/list/__init__.py
nettime_py/schemas/containers/list/employees.py
nettime_py/schemas/containers/list/planning.py
nettime_py/schemas/containers/list/readers.py
nettime_py/schemas/containers/responses/__init__.py
nettime_py/schemas/containers/responses/delete.py
nettime_py-0.1.5.dist-info/LICENSE
nettime_py-0.1.5.dist-info/METADATA
nettime_py-0.1.5.dist-info/WHEEL
nettime_py-0.1.5.dist-info/top_level.txt
nettime_py-0.1.5.dist-info/RECORD
