Metadata-Version: 2.1
Name: nettime-py
Version: 0.1.5
Summary: Python package to consume netTime application by SPEC, SA.
Home-page: https://github.com/lucaslucyk/nettime-py
Author: Lucas Lucyk
Author-email: lucaslucyk@gmail.com
Classifier: Programming Language :: Python :: 3
Classifier: License :: OSI Approved :: GNU General Public License v3 or later (GPLv3+)
Classifier: Operating System :: OS Independent
Requires-Python: >=3.8
License-File: LICENSE
Requires-Dist: requests
Requires-Dist: pydantic >=2.3.0
Requires-Dist: pydantic-core >=2.6.3
Requires-Dist: pydantic-settings >=2.0.3
